{
  "data": [
    {
      "key": "1",
      "icon": { "icon": "icon/success.svg" },
      "ranking": "1",
      "address": { "name": "0xb44f857dasf", "icon": "icon/user-1.svg" },
      "pledge": { "quantity": "4,000", "link": "link1" },
      "staked": "2,000",
      "dripped": "5,432",
      "emmited": "142,235",
      "balance": "W1"
    },
    {
      "key": "2",
      "icon": { "icon": "icon/vector-g.svg" },
      "ranking": "2",
      "address": { "name": "0xb44f857dasf", "icon": "icon/user.svg" },
      "pledge": { "quantity": "4,000", "link": "link2" },
      "staked": "2,000",
      "dripped": "5,432",
      "emmited": "142,235",
      "balance": "W1"
    },
    {
      "key": "3",
      "icon": { "icon": "icon/vector-1.svg" },
      "ranking": "3",
      "address": { "name": "0xb44f857dasf", "icon": "icon/user-1.svg" },
      "pledge": { "quantity": "4,000", "link": "link3" },
      "staked": "2,000",
      "dripped": "5,432",
      "emmited": "142,235",
      "balance": "W1"
    },
    {
      "key": "4",
      "icon": { "icon": "" },
      "ranking": "4",
      "address": { "name": "0xb44f857dasf", "icon": "icon/user.svg" },
      "pledge": { "quantity": "4,000", "link": "link4" },
      "staked": "2,000",
      "dripped": "5,432",
      "emmited": "142,235",
      "balance": "W1"
    },
    {
      "key": "5",
      "icon": { "icon": "" },
      "ranking": "5",
      "address": { "name": "0xb44f857dasf", "icon": "icon/user-1.svg" },
      "pledge": { "quantity": "4,000", "link": "link5" },
      "staked": "2,000",
      "dripped": "5,432",
      "emmited": "142,235",
      "balance": "W1"
    },
    {
      "key": "6",
      "icon": { "icon": "" },
      "ranking": "6",
      "address": { "name": "0xb44f857dasf", "icon": "icon/user.svg" },
      "pledge": { "quantity": "4,000", "link": "link6" },
      "staked": "2,000",
      "dripped": "5,432",
      "emmited": "142,235",
      "balance": "W1"
    },
    {
      "key": "7",
      "icon": { "icon": "" },
      "ranking": "7",
      "address": { "name": "0xb44f857dasf", "icon": "icon/user-1.svg" },
      "pledge": { "quantity": "4,000", "link": "link7" },
      "staked": "2,000",
      "dripped": "5,432",
      "emmited": "142,235",
      "balance": "W1"
    },
    {
      "key": "8",
      "icon": { "icon": "icon/vector.svg" },
      "ranking": "8",
      "address": { "name": "0xb44f857dasf", "icon": "icon/user.svg" },
      "pledge": { "quantity": "4,000", "link": "link8" },
      "staked": "2,000",
      "dripped": "5,432",
      "emmited": "142,235",
      "balance": "W1"
    }
  ]
}
